pymsaviz/__init__.py
pymsaviz/msaviz.py
pymsaviz/config/__init__.py
pymsaviz/config/color_schemes.tsv
pymsaviz/config/testdata/HIGD2A.fa
pymsaviz/config/testdata/MRGPRG.fa
pymsaviz/scripts/__init__.py
pymsaviz/scripts/cli.py
pymsaviz-0.5.0.dist-info/METADATA
pymsaviz-0.5.0.dist-info/WHEEL
pymsaviz-0.5.0.dist-info/entry_points.txt
pymsaviz-0.5.0.dist-info/licenses/LICENSE
pymsaviz-0.5.0.dist-info/RECORD
