Metadata-Version: 2.3
Name: pyMSAviz
Version: 0.5.0
Summary: MSA visualization python package for sequence analysis
Project-URL: homepage, https://moshi4.github.io/pyMSAviz/
Project-URL: repository, https://github.com/moshi4/pyMSAviz/
Author: moshi4
License-Expression: MIT
License-File: LICENSE
Keywords: bioinformatics,matplotlib,sequence-alignment,sequence-analysis,visualization
Classifier: Framework :: Matplotlib
Classifier: Intended Audience :: Science/Research
Classifier: Topic :: Scientific/Engineering :: Bio-Informatics
Requires-Python: >=3.9
Requires-Dist: biopython>=1.79
Requires-Dist: matplotlib>=3.5.2
